quickbeserverless/__init__.py
quickbeserverless-1.3.0.dist-info/LICENSE
quickbeserverless-1.3.0.dist-info/METADATA
quickbeserverless-1.3.0.dist-info/WHEEL
quickbeserverless-1.3.0.dist-info/top_level.txt
quickbeserverless-1.3.0.dist-info/RECORD
