Metadata-Version: 2.1
Name: quickbeserverless
Version: 1.3.0
Summary: Run your function on serverless platform
Home-page: https://github.com/eldad1221/quickbeserverless
Author: Eldad Bishari
Author-email: eldad@1221tlv.org
Classifier: Programming Language :: Python :: 3
Classifier: License :: OSI Approved :: MIT License
Classifier: Operating System :: OS Independent
Requires-Python: >=3.8
License-File: LICENSE
Requires-Dist: cerberus (==1.3.4)
Requires-Dist: quickbelog
